Metadata-Version: 2.4
Name: edc-notification
Version: 1.0.1
Summary: Simple notification classes for clinicedc/edc projects
Home-page: https://github.com/clinicedc/edc-notification
Author: Erik van Widenfelt
Author-email: ew2789@gmail.com
License: GPL license, see LICENSE
Keywords: django Edc notification,clinicedc,clinical trials
Classifier: Environment :: Web Environment
Classifier: Framework :: Django
Classifier: Framework :: Django :: 5.1
Classifier: Intended Audience :: Developers
Classifier: Intended Audience :: Science/Research
Classifier: Operating System :: OS Independent
Classifier: Programming Language :: Python :: 3.12
Classifier: License :: OSI Approved :: GNU General Public License v3 (GPLv3)
Requires-Python: >=3.11
License-File: LICENSE
License-File: AUTHORS
Requires-Dist: requests
Requires-Dist: twilio
Dynamic: license-file
